obfsimp/__init__.py
obfsimp/cli.py
obfsimp/examples/__init__.py
obfsimp/examples/count-obf.py
obfsimp/examples/count.py
obfsimp/examples/fib-obf.py
obfsimp/examples/fib.py
obfsimp/examples/hello-obf.py
obfsimp/examples/hello.py
obfsimp/examples/simple_import-obf.py
obfsimp/examples/simple_import.py
obfsimp/methods/__init__.py
obfsimp/methods/add_code.py
obfsimp/methods/error_free.py
obfsimp/methods/execexp.py
obfsimp/methods/magic.py
obfsimp/methods/remove_comments.py
obfsimp/methods/rename_variables.py
obfsimp/methods/stringobf.py
obfsimp-1.0.1.dist-info/METADATA
obfsimp-1.0.1.dist-info/WHEEL
obfsimp-1.0.1.dist-info/entry_points.txt
obfsimp-1.0.1.dist-info/top_level.txt
obfsimp-1.0.1.dist-info/RECORD
