Metadata-Version: 2.1
Name: obfsimp
Version: 1.0.1
Summary: Simple Python 3 obfuscator
Home-page: https://github.com/none-None1/obfsimp
Keywords: obfuscator
Classifier: Programming Language :: Python :: 3 :: Only
Classifier: Operating System :: OS Independent
Requires-Python: >=3
Requires-Dist: pygments
